rainy/__init__.py
rainy/cli.py
rainy/config.py
rainy/experiment.py
rainy/ipython.py
rainy/prelude.py
rainy/run.py
rainy/agent/__init__.py
rainy/agent/base.py
rainy/agent/dqn.py
rainy/agents/__init__.py
rainy/agents/a2c.py
rainy/agents/acktr.py
rainy/agents/actc.py
rainy/agents/aoc.py
rainy/agents/base.py
rainy/agents/bootdqn.py
rainy/agents/ddpg.py
rainy/agents/ddqn.py
rainy/agents/dqn.py
rainy/agents/ppo.py
rainy/agents/ppoc.py
rainy/agents/sac.py
rainy/agents/td3.py
rainy/agents/wrappers.py
rainy/env_ext/__init__.py
rainy/env_ext/atari_wrappers.py
rainy/envs/__init__.py
rainy/envs/atari_wrappers.py
rainy/envs/cartpole_ext.py
rainy/envs/deepsea.py
rainy/envs/ext.py
rainy/envs/monitor.py
rainy/envs/obs_wrappers.py
rainy/envs/parallel.py
rainy/envs/parallel_wrappers.py
rainy/envs/swingup.py
rainy/envs/testing.py
rainy/explore/__init__.py
rainy/explore/base.py
rainy/explore/cooler.py
rainy/explore/strategies.py
rainy/explore/test_explore.py
rainy/lib/__init__.py
rainy/lib/explore.py
rainy/lib/hooks.py
rainy/lib/kfac.py
rainy/lib/mpi.py
rainy/lib/rollout.py
rainy/net/__init__.py
rainy/net/actor_critic.py
rainy/net/block.py
rainy/net/body.py
rainy/net/bootstrap.py
rainy/net/deterministic.py
rainy/net/dilated.py
rainy/net/head.py
rainy/net/init.py
rainy/net/misc.py
rainy/net/option_critic.py
rainy/net/policy.py
rainy/net/prelude.py
rainy/net/recurrent.py
rainy/net/sac.py
rainy/net/termination_critic.py
rainy/net/value.py
rainy/net/value_net.py
rainy/replay/__init__.py
rainy/replay/array_deque.py
rainy/replay/base.py
rainy/replay/test_deque.py
rainy/replay/uniform.py
rainy/util/__init__.py
rainy/util/device.py
rainy/util/log.py
rainy/util/sample.py
rainy/utils/__init__.py
rainy/utils/cli.py
rainy/utils/device.py
rainy/utils/log.py
rainy/utils/misc.py
rainy/utils/mp_utils.py
rainy/utils/rms.py
rainy/utils/sample.py
rainy/utils/state_dict.py
rainy/utils/test_rms.py
rainy/utils/test_sample.py
rainy-0.8.0.dist-info/LICENSE
rainy-0.8.0.dist-info/METADATA
rainy-0.8.0.dist-info/WHEEL
rainy-0.8.0.dist-info/top_level.txt
rainy-0.8.0.dist-info/RECORD
