Metadata-Version: 2.1
Name: rainy
Version: 0.8.0
Summary: Algorithm and utilities for deep reinforcement learning
Home-page: https://github.com/kngwyu/Rainy
Author: Yuji Kanagawa
Author-email: yuji.kngw.80s.revive@gmail.com
License: Apache2
Project-URL: Code, https://github.com/kngwyu/Rainy
Project-URL: Issue tracker, https://github.com/kngwyu/Rainy/issues
Platform: UNKNOWN
Classifier: License :: OSI Approved :: Apache Software License
Classifier: Development Status :: 3 - Alpha
Classifier: Intended Audience :: Science/Research
Classifier: Natural Language :: English
Classifier: Operating System :: OS Independent
Classifier: Programming Language :: Python
Classifier: Programming Language :: Python :: 3
Classifier: Programming Language :: Python :: 3.6
Classifier: Programming Language :: Python :: 3.7
Classifier: Programming Language :: Python :: Implementation :: CPython
Requires-Python: >=3.6.0
Requires-Dist: click (>=7.0)
Requires-Dist: colorama (>=0.4)
Requires-Dist: GitPython (>=2.0)
Requires-Dist: gym[atari] (>=0.11.0)
Requires-Dist: numpy (>=1.15.0)
Requires-Dist: opencv-python (>=3.4)
Requires-Dist: pandas (>=0.25)
Requires-Dist: torch (>=1.2)
Provides-Extra: bullet
Requires-Dist: pybullet (>=2.4) ; extra == 'bullet'
Provides-Extra: horovod
Requires-Dist: horovod (>=0.16) ; extra == 'horovod'
Provides-Extra: rlpy
Requires-Dist: rlpy3 (>=2.0.0b1) ; extra == 'rlpy'
